randevu/__init__.py
randevu/randevu.py
randevu-2.0.3.dist-info/LICENSE.md
randevu-2.0.3.dist-info/METADATA
randevu-2.0.3.dist-info/WHEEL
randevu-2.0.3.dist-info/top_level.txt
randevu-2.0.3.dist-info/RECORD
