Metadata-Version: 2.2
Name: randevu
Version: 2.0.3
Summary: The official Python implementation of the RANDEVU algorithm
Author: TypicalHog
License: This work is released into the public domain with The Unlicense.
Project-URL: Homepage, https://github.com/TypicalHog/randevu-py
Project-URL: Issues, https://github.com/TypicalHog/randevu-py/issues
Keywords: randevu,rdv,rdvt,universal,daily,reminder,coordination,blake3
Classifier: Programming Language :: Python :: 3
Classifier: License :: OSI Approved :: The Unlicense (Unlicense)
Classifier: License :: OSI Approved :: MIT License
Classifier: License :: OSI Approved :: Apache Software License
Classifier: Operating System :: OS Independent
Requires-Python: >=3.8
License-File: LICENSE.md
Requires-Dist: blake3>=1.0.4
